pogosim/__init__.py
pogosim/arenas.py
pogosim/compute_optimal_psend.py
pogosim/convert_and_scale_svg.py
pogosim/coverage.py
pogosim/locomotion.py
pogosim/neighbors.py
pogosim/pogobatch.py
pogosim/pogoptim.py
pogosim/scale_csv_arena.py
pogosim/utils.py
pogosim-0.10.7.dist-info/METADATA
pogosim-0.10.7.dist-info/WHEEL
pogosim-0.10.7.dist-info/entry_points.txt
pogosim-0.10.7.dist-info/top_level.txt
pogosim-0.10.7.dist-info/RECORD
