Metadata-Version: 2.4
Name: pogosim
Version: 0.10.7
Summary: Pogobot Batch Runner
Home-page: https://github.com/Adacoma/pogosim
Author: Leo Cazenille
Author-email: leo.cazenille@gmail.com
Classifier: Programming Language :: Python :: 3
Classifier: Operating System :: OS Independent
Requires-Python: >=3.9
Requires-Dist: pyyaml>=5.3
Requires-Dist: pandas>=1.3.0
Requires-Dist: pyarrow>=19.0.0
Dynamic: author
Dynamic: author-email
Dynamic: classifier
Dynamic: description
Dynamic: description-content-type
Dynamic: home-page
Dynamic: requires-dist
Dynamic: requires-python
Dynamic: summary
